drf_nested_field_multipart/__init__.py
drf_nested_field_multipart/parser.py
drf_nested_field_multipart-0.0.3.dist-info/DESCRIPTION.rst
drf_nested_field_multipart-0.0.3.dist-info/METADATA
drf_nested_field_multipart-0.0.3.dist-info/RECORD
drf_nested_field_multipart-0.0.3.dist-info/WHEEL
drf_nested_field_multipart-0.0.3.dist-info/metadata.json
drf_nested_field_multipart-0.0.3.dist-info/top_level.txt
