Metadata-Version: 2.0
Name: drf-nested-field-multipart
Version: 0.0.3
Summary: Parser for nested params in multipart file upload
Home-page: https://github.com/ah450/drf-nested-field-multipart
Author: Ahmed Hisham Ismail
Author-email: ahm3d.hisham@gmail.com
License: MIT
Platform: UNKNOWN
Classifier: Environment :: Web Environment
Classifier: Framework :: Django
Classifier: Framework :: Django :: 1.10
Classifier: Intended Audience :: Developers
Classifier: Programming Language :: Python
Classifier: Programming Language :: Python :: 3
Classifier: Topic :: Internet :: WWW/HTTP
Classifier: License :: OSI Approved :: MIT License
